nbtrash/__init__.py
nbtrash/etc/nbext_trash.json
nbtrash/etc/server_trash.json
nbtrash/static/main.js
nbtrash/static/tree.css
nbtrash-0.1.3.data/data/etc/jupyter/jupyter_notebook_config.d/server_trash.json
nbtrash-0.1.3.data/data/etc/jupyter/nbconfig/notebook.d/nbext_trash.json
nbtrash-0.1.3.data/data/share/jupyter/nbextensions/nbtrash/main.js
nbtrash-0.1.3.data/data/share/jupyter/nbextensions/nbtrash/tree.css
nbtrash-0.1.3.dist-info/LICENSE
nbtrash-0.1.3.dist-info/METADATA
nbtrash-0.1.3.dist-info/WHEEL
nbtrash-0.1.3.dist-info/top_level.txt
nbtrash-0.1.3.dist-info/RECORD
